octo_pipeline_python/backends/cppcheck/__init__.py
octo_pipeline_python/backends/cppcheck/cppcheck_backend.py
octo_pipeline_python/backends/cppcheck/actions/__init__.py
octo_pipeline_python/backends/cppcheck/actions/cppcheck_code_check.py
octo_pipeline_python/backends/cppcheck/models/__init__.py
octo_pipeline_python/backends/cppcheck/models/cppcheck_model.py
octo_pipeline_backend_cppcheck_python-1.3.2.dist-info/LICENSE.txt
octo_pipeline_backend_cppcheck_python-1.3.2.dist-info/METADATA
octo_pipeline_backend_cppcheck_python-1.3.2.dist-info/README.md
octo_pipeline_backend_cppcheck_python-1.3.2.dist-info/WHEEL
octo_pipeline_backend_cppcheck_python-1.3.2.dist-info/top_level.txt
octo_pipeline_backend_cppcheck_python-1.3.2.dist-info/RECORD
